{"dataPathRelativeToProjectURL":"..\/..\/..\/HackingWithSwift\/SwiftUI\/project4-files\/BetterRest.csv\/","title":"BetterRest.csv","id":"C5897A4B-D680-44C7-90A9-42052F7632F5","experimentIDs":["00B7AF53-2596-43E4-8FCC-4AADCF57418C"],"dataURL":"file:\/\/\/Users\/j\/repos\/learning\/HackingWithSwift\/SwiftUI\/project4-files\/BetterRest.csv","dataResult":{"dataURL":"file:\/\/\/Users\/j\/repos\/learning\/HackingWithSwift\/SwiftUI\/project4-files\/BetterRest.csv","createdDate":"2024-05-16T20:12:27Z","dataSourceID":"C5897A4B-D680-44C7-90A9-42052F7632F5"},"activityEntities":["dataSourceTrainingStarted",[{"event":"dataSourceTrainingStarted","createdDate":"2024-05-16T20:13:38Z","title":"Used By","id":"04013D84-BAAF-4C6C-A4B7-67DCB4A4D08A","subtitle":"OptimalSleepModel 1"}],"dataSourceMetrics",[{"id":"57A6D3F2-FAA2-4549-A6AE-0BDEBADE2E02","event":"dataSourceMetrics","subtitle":"10,000 Items","title":"Data Summary","createdDate":"2024-05-16T20:13:38Z"}]],"version":"1.0","pathType":0,"modifiedDate":"2024-05-16T20:13:38Z","createdDate":"2024-05-16T20:12:27Z","preferredFilename":"BetterRest.csv"}